LICENSE
README.md
setup.py
ao/__init__.py
ao/signer.py
aodotpy.egg-info/PKG-INFO
aodotpy.egg-info/SOURCES.txt
aodotpy.egg-info/dependency_links.txt
aodotpy.egg-info/requires.txt
aodotpy.egg-info/top_level.txt