Metadata-Version: 2.1
Name: aodotpy
Version: 0.2.3
Summary: Python wrappers for ao
Home-page: https://github.com/permadao/ao.py
Download-URL: https://github.com/xiaojay/permadao/archive/refs/tags/v0.2.3.tar.gz
Author: xiaojay
Author-email: xiaojay@gmail.com
License: MIT
Classifier: Programming Language :: Python :: 3
Classifier: Programming Language :: Python :: 2
Classifier: License :: OSI Approved :: MIT License
Classifier: Operating System :: OS Independent
License-File: LICENSE
